Workbook
Name Bancos: Parâmetros!$C$4:$C$11
Name despesas: Parâmetros!$A$4:$A$20
Name receitas: Parâmetros!$B$4:$B$20

Sheet Parâmetros
A1: Preencha essa aba com as categorias de Despesas e Receitas que serão utilizadas em seu dia a dia. Também Preencha as formas de pagamento que você costuma Utilizar. Qualquer dúvida ou sugestão entre em contato com nossa equipe pelo link abaixo: | G1: Desenvolvido por:
A2: Whatsapp 47 3180-4931 | H2: oasystecnologia.com
A3: DESPESAS | B3: RECEITAS | C3: Formas de Pagamento
A4: Fornecedores | B4: Previsão de receita de Vendas | C4: Caixa
A5: Aluguel/Condomínio | B5: Receita de Vendas - Realizada | C5: Banco do Brasil
A6: Energia Elétrica | B6: Prestação de Serviços | C6: Nubank
A7: Folha de Pagamento / Pró-labore | B7: Receitas Financeiras (Juros/ Rendimentos Recebidos) | C7: Banco Inter
A8: Encargos Trabalhistas | B8: Outras Receitas Operacionais
A9: Contabilidade
A10: Licenças de Software/Sistemas
A11: Matéria Prima / Mercadorias
A12: Frete
A13: Comissões de Vendas
A14: Taxas de Cartão / Gateways de Pagamento

Sheet Demonstrativo Anual
A1: Demonstrativo Anual
A2: (Os dados serão preenchidos automaticamente conforme você preencher as páginas mensais)
A4: JANEIRO | D4: FEVEREIRO | G4: MARÇO | J4: ABRIL | M4: MAIO | P4: JUNHO
A5: SALDO ANTERIOR | B5: =JAN!H2 -> 10000 | D5: SALDO ANTERIOR | E5: =B8 -> 9603.78 | G5: SALDO ANTERIOR | H5: =E8 -> 9603.78 | J5: SALDO ANTERIOR | K5: =H8 -> 9603.78 | M5: SALDO ANTERIOR | N5: =K8 -> 9603.78 | P5: SALDO ANTERIOR | Q5: =N8 -> 9603.78
A6: TOTAL ENTRADAS | B6: =SUMIF(JAN!A7:A207,"Receitas",JAN!E7:E207) -> 26 | D6: TOTAL ENTRADAS | E6: =SUMIF(FEV!D7:D207,"Receitas",FEV!H7:H207) -> 0 | G6: TOTAL ENTRADAS | H6: =SUMIF(MAR!G7:G207,"Receitas",MAR!K7:K207) -> 0 | J6: TOTAL ENTRADAS | K6: =SUMIF(ABR!J7:J207,"Receitas",ABR!N7:N207) -> 0 | M6: TOTAL ENTRADAS | N6: =SUMIF(MAI!M7:M207,"Receitas",MAI!Q7:Q207) -> 0 | P6: TOTAL ENTRADAS | Q6: =SUMIF(JUN!P7:P207,"Receitas",JUN!T7:T207) -> 0
A7: TOTAL SAÍDAS | B7: =SUMIF(JAN!A8:A208,"Despesas",JAN!E8:E208) -> 422.22 | D7: TOTAL SAÍDAS | E7: =SUMIF(FEV!D8:D208,"Despesas",FEV!H8:H208) -> 0 | G7: TOTAL SAÍDAS | H7: =SUMIF(MAR!G8:G208,"Despesas",MAR!K8:K208) -> 0 | J7: TOTAL SAÍDAS | K7: =SUMIF(ABR!J8:J208,"Despesas",ABR!N8:N208) -> 0 | M7: TOTAL SAÍDAS | N7: =SUMIF(MAI!M8:M208,"Despesas",MAI!Q8:Q208) -> 0 | P7: TOTAL SAÍDAS | Q7: =SUMIF(JUN!P8:P208,"Despesas",JUN!T8:T208) -> 0
A8: SALDO FINAL | B8: =B5+B6-B7 -> 9603.78 | D8: SALDO FINAL | E8: =E5+E6+E7 -> 9603.78 | G8: SALDO FINAL | H8: =H5+H6+H7 -> 9603.78 | J8: SALDO FINAL | K8: =K5+K6+K7 -> 9603.78 | M8: SALDO FINAL | N8: =N5+N6+N7 -> 9603.78 | P8: SALDO FINAL | Q8: =Q5+Q6+Q7 -> 9603.78
A10: JULHO | D10: AGOSTO | G10: SETEMBRO | J10: OUTUBRO | M10: NOVEMBRO | P10: DEZEMBRO
A11: SALDO ANTERIOR | B11: =Q8 -> 9603.78 | D11: SALDO ANTERIOR | E11: =B14 -> 9603.78 | G11: SALDO ANTERIOR | H11: =E14 -> 9603.78 | J11: SALDO ANTERIOR | K11: =H14 -> 9603.78 | M11: SALDO ANTERIOR | N11: =K14 -> 9603.78 | P11: SALDO ANTERIOR | Q11: =N14 -> 9603.78
A12: TOTAL ENTRADAS | B12: =SUMIF(JUL!A13:A213,"Receitas",JUL!E13:E213) -> 0 | D12: TOTAL ENTRADAS | E12: =SUMIF(AGO!D13:D213,"Receitas",AGO!H13:H213) -> 0 | G12: TOTAL ENTRADAS | H12: =SUMIF(SET!G13:G213,"Receitas",SET!K13:K213) -> 0 | J12: TOTAL ENTRADAS | K12: =SUMIF(OUT!J13:J213,"Receitas",OUT!N13:N213) -> 0 | M12: TOTAL ENTRADAS | N12: =SUMIF(NOV!M13:M213,"Receitas",NOV!Q13:Q213) -> 0 | P12: TOTAL ENTRADAS | Q12: =SUMIF(DEZ!P13:P213,"Receitas",DEZ!T13:T213) -> 0
A13: TOTAL SAÍDAS | B13: =SUMIF(JUL!A14:A214,"Despesas",JUL!E14:E214) -> 0 | D13: TOTAL SAÍDAS | E13: =SUMIF(AGO!D14:D214,"Despesas",AGO!H14:H214) -> 0 | G13: TOTAL SAÍDAS | H13: =SUMIF(SET!G14:G214,"Despesas",SET!K14:K214) -> 0 | J13: TOTAL SAÍDAS | K13: =SUMIF(OUT!J14:J214,"Despesas",OUT!N14:N214) -> 0 | M13: TOTAL SAÍDAS | N13: =SUMIF(NOV!M14:M214,"Despesas",NOV!Q14:Q214) -> 0 | P13: TOTAL SAÍDAS | Q13: =SUMIF(DEZ!P14:P214,"Despesas",DEZ!T14:T214) -> 0
A14: SALDO FINAL | B14: =B11+B12+B13 -> 9603.78 | D14: SALDO FINAL | E14: =E11+E12+E13 -> 9603.78 | G14: SALDO FINAL | H14: =H11+H12+H13 -> 9603.78 | J14: SALDO FINAL | K14: =K11+K12+K13 -> 9603.78 | M14: SALDO FINAL | N14: =N11+N12+N13 -> 9603.78 | P14: SALDO FINAL | Q14: =Q11+Q12+Q13 -> 9603.78
P30: Desenvolvido por:

Sheet JAN
C1: Janeiro | F1: Preencha com o Saldo Inicial » | H1: SALDO ANTERIOR:
H2: 10000
A5: Tipo | B5: Categoria | C5: Forma de Pagamento | D5: Observações | E5: Valor | F5: Data | G5: MOV | H5: Saldo
D6: SALDO INICIAL | E6: =H2 -> 10000 | F6: 45657 | G6: =E6 -> 10000 | H6: =E6 -> 10000
A7: Receitas | B7: Previsão de receita de Vendas | C7: Caixa | D7: EXEMPLO | E7: 26 | F7: 45658 | G7: =IF(A7="Despesas",E7*-1,IF(A7="Receitas",E7,0)) -> 26 | H7: =H6+G7 -> 10026
A8: Despesas | B8: Comissões de Vendas | C8: Banco do Brasil | D8: EXEMPLO | E8: 422.22 | F8: 45659 | G8: =IF(A8="Despesas",E8*-1,IF(A8="Receitas",E8,0)) -> -422.22 | H8: =H7+G8 -> 9603.78
G9: =IF(A9="Despesas",E9*-1,IF(A9="Receitas",E9,0)) -> 0 | H9: =H8+G9 -> 9603.78
G10: =IF(A10="Despesas",E10*-1,IF(A10="Receitas",E10,0)) -> 0 | H10: =H9+G10 -> 9603.78
G11: =IF(A11="Despesas",E11*-1,IF(A11="Receitas",E11,0)) -> 0 | H11: =H10+G11 -> 9603.78
G12: =IF(A12="Despesas",E12*-1,IF(A12="Receitas",E12,0)) -> 0 | H12: =H11+G12 -> 9603.78
G13: =IF(A13="Despesas",E13*-1,IF(A13="Receitas",E13,0)) -> 0 | H13: =H12+G13 -> 9603.78
G14: =IF(A14="Despesas",E14*-1,IF(A14="Receitas",E14,0)) -> 0 | H14: =H13+G14 -> 9603.78
G15: =IF(A15="Despesas",E15*-1,IF(A15="Receitas",E15,0)) -> 0 | H15: =H14+G15 -> 9603.78
G16: =IF(A16="Despesas",E16*-1,IF(A16="Receitas",E16,0)) -> 0 | H16: =H15+G16 -> 9603.78
G17: =IF(A17="Despesas",E17*-1,IF(A17="Receitas",E17,0)) -> 0 | H17: =H16+G17 -> 9603.78
G18: =IF(A18="Despesas",E18*-1,IF(A18="Receitas",E18,0)) -> 0 | H18: =H17+G18 -> 9603.78
G19: =IF(A19="Despesas",E19*-1,IF(A19="Receitas",E19,0)) -> 0 | H19: =H18+G19 -> 9603.78
G20: =IF(A20="Despesas",E20*-1,IF(A20="Receitas",E20,0)) -> 0 | H20: =H19+G20 -> 9603.78
... G206: =IF(A206="Despesas",E206*-1,IF(A206="Receitas",E206,0)) -> 0 | H206: =H205+G206 -> 9603.78
A207: Fim | B207: FIM | C207: Fim | D207: Fim | E207: Fim | F207: Fim | G207: Fim | H207: FIM

Sheet FEV
C1: Fevereiro | F1: Preencha com o Saldo Inicial » | H1: SALDO ANTERIOR:
H2: =JAN!H206 -> 9603.78
A5: Tipo | B5: Categoria | C5: Forma de Pagamento | D5: Observações | E5: Valor | F5: Data | G5: MOV | H5: Saldo
D6: SALDO INICIAL | E6: =H2 -> 9603.78 | F6: 46053 | G6: =E6 -> 9603.78 | H6: =E6 -> 9603.78
A7: Receitas | B7: Previsão de receita de Vendas | E7: 5 | G7: =IF(A7="Despesas",E7*-1,IF(A7="Receitas",E7,0)) -> 5 | H7: =H6+G7 -> 9608.78
G8: =IF(A8="Despesas",E8*-1,IF(A8="Receitas",E8,0)) -> 0 | H8: =H7+G8 -> 9608.78
G9: =IF(A9="Despesas",E9*-1,IF(A9="Receitas",E9,0)) -> 0 | H9: =H8+G9 -> 9608.78
G10: =IF(A10="Despesas",E10*-1,IF(A10="Receitas",E10,0)) -> 0 | H10: =H9+G10 -> 9608.78
G11: =IF(A11="Despesas",E11*-1,IF(A11="Receitas",E11,0)) -> 0 | H11: =H10+G11 -> 9608.78
G12: =IF(A12="Despesas",E12*-1,IF(A12="Receitas",E12,0)) -> 0 | H12: =H11+G12 -> 9608.78
G13: =IF(A13="Despesas",E13*-1,IF(A13="Receitas",E13,0)) -> 0 | H13: =H12+G13 -> 9608.78
G14: =IF(A14="Despesas",E14*-1,IF(A14="Receitas",E14,0)) -> 0 | H14: =H13+G14 -> 9608.78
G15: =IF(A15="Despesas",E15*-1,IF(A15="Receitas",E15,0)) -> 0 | H15: =H14+G15 -> 9608.78
G16: =IF(A16="Despesas",E16*-1,IF(A16="Receitas",E16,0)) -> 0 | H16: =H15+G16 -> 9608.78
G17: =IF(A17="Despesas",E17*-1,IF(A17="Receitas",E17,0)) -> 0 | H17: =H16+G17 -> 9608.78
G18: =IF(A18="Despesas",E18*-1,IF(A18="Receitas",E18,0)) -> 0 | H18: =H17+G18 -> 9608.78
G19: =IF(A19="Despesas",E19*-1,IF(A19="Receitas",E19,0)) -> 0 | H19: =H18+G19 -> 9608.78
... G206: =IF(A206="Despesas",E206*-1,IF(A206="Receitas",E206,0)) -> 0 | H206: =H205+G206 -> 9608.78
A207: Fim | B207: FIM | C207: Fim | D207: Fim | E207: Fim | F207: Fim | G207: Fim | H207: FIM

Sheet MAR
C1: Março | F1: Preencha com o Saldo Inicial » | H1: SALDO ANTERIOR:
H2: =FEV!H206 -> 9608.78
A5: Tipo | B5: Categoria | C5: Forma de Pagamento | D5: Observações | E5: Valor | F5: Data | G5: MOV | H5: Saldo
D6: SALDO INICIAL | E6: =H2 -> 9608.78 | F6: 46081 | G6: =E6 -> 9608.78 | H6: =E6 -> 9608.78
G7: =IF(A7="Despesas",E7*-1,IF(A7="Receitas",E7,0)) -> 0 | H7: =H6+G7 -> 9608.78
G8: =IF(A8="Despesas",E8*-1,IF(A8="Receitas",E8,0)) -> 0 | H8: =H7+G8 -> 9608.78
G9: =IF(A9="Despesas",E9*-1,IF(A9="Receitas",E9,0)) -> 0 | H9: =H8+G9 -> 9608.78
G10: =IF(A10="Despesas",E10*-1,IF(A10="Receitas",E10,0)) -> 0 | H10: =H9+G10 -> 9608.78
G11: =IF(A11="Despesas",E11*-1,IF(A11="Receitas",E11,0)) -> 0 | H11: =H10+G11 -> 9608.78
G12: =IF(A12="Despesas",E12*-1,IF(A12="Receitas",E12,0)) -> 0 | H12: =H11+G12 -> 9608.78
G13: =IF(A13="Despesas",E13*-1,IF(A13="Receitas",E13,0)) -> 0 | H13: =H12+G13 -> 9608.78
G14: =IF(A14="Despesas",E14*-1,IF(A14="Receitas",E14,0)) -> 0 | H14: =H13+G14 -> 9608.78
G15: =IF(A15="Despesas",E15*-1,IF(A15="Receitas",E15,0)) -> 0 | H15: =H14+G15 -> 9608.78
G16: =IF(A16="Despesas",E16*-1,IF(A16="Receitas",E16,0)) -> 0 | H16: =H15+G16 -> 9608.78
G17: =IF(A17="Despesas",E17*-1,IF(A17="Receitas",E17,0)) -> 0 | H17: =H16+G17 -> 9608.78
G18: =IF(A18="Despesas",E18*-1,IF(A18="Receitas",E18,0)) -> 0 | H18: =H17+G18 -> 9608.78
... G206: =IF(A206="Despesas",E206*-1,IF(A206="Receitas",E206,0)) -> 0 | H206: =H205+G206 -> 9608.78
A207: Fim | B207: FIM | C207: Fim | D207: Fim | E207: Fim | F207: Fim | G207: Fim | H207: FIM

Sheet ABR
C1: Abril | F1: Preencha com o Saldo Inicial » | H1: SALDO ANTERIOR:
H2: =MAR!H206 -> 9608.78
A5: Tipo | B5: Categoria | C5: Forma de Pagamento | D5: Observações | E5: Valor | F5: Data | G5: MOV | H5: Saldo
D6: SALDO INICIAL | E6: =H2 -> 9608.78 | F6: 46112 | G6: =E6 -> 9608.78 | H6: =E6 -> 9608.78
G7: =IF(A7="Despesas",E7*-1,IF(A7="Receitas",E7,0)) -> 0 | H7: =H6+G7 -> 9608.78
G8: =IF(A8="Despesas",E8*-1,IF(A8="Receitas",E8,0)) -> 0 | H8: =H7+G8 -> 9608.78
G9: =IF(A9="Despesas",E9*-1,IF(A9="Receitas",E9,0)) -> 0 | H9: =H8+G9 -> 9608.78
G10: =IF(A10="Despesas",E10*-1,IF(A10="Receitas",E10,0)) -> 0 | H10: =H9+G10 -> 9608.78
G11: =IF(A11="Despesas",E11*-1,IF(A11="Receitas",E11,0)) -> 0 | H11: =H10+G11 -> 9608.78
G12: =IF(A12="Despesas",E12*-1,IF(A12="Receitas",E12,0)) -> 0 | H12: =H11+G12 -> 9608.78
G13: =IF(A13="Despesas",E13*-1,IF(A13="Receitas",E13,0)) -> 0 | H13: =H12+G13 -> 9608.78
G14: =IF(A14="Despesas",E14*-1,IF(A14="Receitas",E14,0)) -> 0 | H14: =H13+G14 -> 9608.78
G15: =IF(A15="Despesas",E15*-1,IF(A15="Receitas",E15,0)) -> 0 | H15: =H14+G15 -> 9608.78
G16: =IF(A16="Despesas",E16*-1,IF(A16="Receitas",E16,0)) -> 0 | H16: =H15+G16 -> 9608.78
G17: =IF(A17="Despesas",E17*-1,IF(A17="Receitas",E17,0)) -> 0 | H17: =H16+G17 -> 9608.78
G18: =IF(A18="Despesas",E18*-1,IF(A18="Receitas",E18,0)) -> 0 | H18: =H17+G18 -> 9608.78
... G206: =IF(A206="Despesas",E206*-1,IF(A206="Receitas",E206,0)) -> 0 | H206: =H205+G206 -> 9608.78
A207: Fim | B207: FIM | C207: Fim | D207: Fim | E207: Fim | F207: Fim | G207: Fim | H207: FIM

Sheet MAI
C1: Maio | F1: Preencha com o Saldo Inicial » | H1: SALDO ANTERIOR:
H2: =ABR!H206 -> 9608.78
A5: Tipo | B5: Categoria | C5: Forma de Pagamento | D5: Observações | E5: Valor | F5: Data | G5: MOV | H5: Saldo
D6: SALDO INICIAL | E6: =H2 -> 9608.78 | F6: 46142 | G6: =E6 -> 9608.78 | H6: =E6 -> 9608.78
G7: =IF(A7="Despesas",E7*-1,IF(A7="Receitas",E7,0)) -> 0 | H7: =H6+G7 -> 9608.78
G8: =IF(A8="Despesas",E8*-1,IF(A8="Receitas",E8,0)) -> 0 | H8: =H7+G8 -> 9608.78
G9: =IF(A9="Despesas",E9*-1,IF(A9="Receitas",E9,0)) -> 0 | H9: =H8+G9 -> 9608.78
G10: =IF(A10="Despesas",E10*-1,IF(A10="Receitas",E10,0)) -> 0 | H10: =H9+G10 -> 9608.78
G11: =IF(A11="Despesas",E11*-1,IF(A11="Receitas",E11,0)) -> 0 | H11: =H10+G11 -> 9608.78
G12: =IF(A12="Despesas",E12*-1,IF(A12="Receitas",E12,0)) -> 0 | H12: =H11+G12 -> 9608.78
G13: =IF(A13="Despesas",E13*-1,IF(A13="Receitas",E13,0)) -> 0 | H13: =H12+G13 -> 9608.78
G14: =IF(A14="Despesas",E14*-1,IF(A14="Receitas",E14,0)) -> 0 | H14: =H13+G14 -> 9608.78
G15: =IF(A15="Despesas",E15*-1,IF(A15="Receitas",E15,0)) -> 0 | H15: =H14+G15 -> 9608.78
G16: =IF(A16="Despesas",E16*-1,IF(A16="Receitas",E16,0)) -> 0 | H16: =H15+G16 -> 9608.78
G17: =IF(A17="Despesas",E17*-1,IF(A17="Receitas",E17,0)) -> 0 | H17: =H16+G17 -> 9608.78
G18: =IF(A18="Despesas",E18*-1,IF(A18="Receitas",E18,0)) -> 0 | H18: =H17+G18 -> 9608.78
... G206: =IF(A206="Despesas",E206*-1,IF(A206="Receitas",E206,0)) -> 0 | H206: =H205+G206 -> 9608.78
A207: Fim | B207: FIM | C207: Fim | D207: Fim | E207: Fim | F207: Fim | G207: Fim | H207: FIM

Sheet JUN
C1: Junho | F1: Preencha com o Saldo Inicial » | H1: SALDO ANTERIOR:
H2: =MAI!H206 -> 9608.78
A5: Tipo | B5: Categoria | C5: Forma de Pagamento | D5: Observações | E5: Valor | F5: Data | G5: MOV | H5: Saldo
D6: SALDO INICIAL | E6: =H2 -> 9608.78 | F6: 46173 | G6: =E6 -> 9608.78 | H6: =E6 -> 9608.78
G7: =IF(A7="Despesas",E7*-1,IF(A7="Receitas",E7,0)) -> 0 | H7: =H6+G7 -> 9608.78
G8: =IF(A8="Despesas",E8*-1,IF(A8="Receitas",E8,0)) -> 0 | H8: =H7+G8 -> 9608.78
G9: =IF(A9="Despesas",E9*-1,IF(A9="Receitas",E9,0)) -> 0 | H9: =H8+G9 -> 9608.78
G10: =IF(A10="Despesas",E10*-1,IF(A10="Receitas",E10,0)) -> 0 | H10: =H9+G10 -> 9608.78
G11: =IF(A11="Despesas",E11*-1,IF(A11="Receitas",E11,0)) -> 0 | H11: =H10+G11 -> 9608.78
G12: =IF(A12="Despesas",E12*-1,IF(A12="Receitas",E12,0)) -> 0 | H12: =H11+G12 -> 9608.78
G13: =IF(A13="Despesas",E13*-1,IF(A13="Receitas",E13,0)) -> 0 | H13: =H12+G13 -> 9608.78
G14: =IF(A14="Despesas",E14*-1,IF(A14="Receitas",E14,0)) -> 0 | H14: =H13+G14 -> 9608.78
G15: =IF(A15="Despesas",E15*-1,IF(A15="Receitas",E15,0)) -> 0 | H15: =H14+G15 -> 9608.78
G16: =IF(A16="Despesas",E16*-1,IF(A16="Receitas",E16,0)) -> 0 | H16: =H15+G16 -> 9608.78
G17: =IF(A17="Despesas",E17*-1,IF(A17="Receitas",E17,0)) -> 0 | H17: =H16+G17 -> 9608.78
G18: =IF(A18="Despesas",E18*-1,IF(A18="Receitas",E18,0)) -> 0 | H18: =H17+G18 -> 9608.78
... G206: =IF(A206="Despesas",E206*-1,IF(A206="Receitas",E206,0)) -> 0 | H206: =H205+G206 -> 9608.78
A207: Fim | B207: FIM | C207: Fim | D207: Fim | E207: Fim | F207: Fim | G207: Fim | H207: FIM

Sheet JUL
C1: Julho | F1: Preencha com o Saldo Inicial » | H1: SALDO ANTERIOR:
H2: =JUN!H206 -> 9608.78
A5: Tipo | B5: Categoria | C5: Forma de Pagamento | D5: Observações | E5: Valor | F5: Data | G5: MOV | H5: Saldo
D6: SALDO INICIAL | E6: =H2 -> 9608.78 | F6: 46203 | G6: =E6 -> 9608.78 | H6: =E6 -> 9608.78
G7: =IF(A7="Despesas",E7*-1,IF(A7="Receitas",E7,0)) -> 0 | H7: =H6+G7 -> 9608.78
G8: =IF(A8="Despesas",E8*-1,IF(A8="Receitas",E8,0)) -> 0 | H8: =H7+G8 -> 9608.78
G9: =IF(A9="Despesas",E9*-1,IF(A9="Receitas",E9,0)) -> 0 | H9: =H8+G9 -> 9608.78
G10: =IF(A10="Despesas",E10*-1,IF(A10="Receitas",E10,0)) -> 0 | H10: =H9+G10 -> 9608.78
G11: =IF(A11="Despesas",E11*-1,IF(A11="Receitas",E11,0)) -> 0 | H11: =H10+G11 -> 9608.78
G12: =IF(A12="Despesas",E12*-1,IF(A12="Receitas",E12,0)) -> 0 | H12: =H11+G12 -> 9608.78
G13: =IF(A13="Despesas",E13*-1,IF(A13="Receitas",E13,0)) -> 0 | H13: =H12+G13 -> 9608.78
G14: =IF(A14="Despesas",E14*-1,IF(A14="Receitas",E14,0)) -> 0 | H14: =H13+G14 -> 9608.78
G15: =IF(A15="Despesas",E15*-1,IF(A15="Receitas",E15,0)) -> 0 | H15: =H14+G15 -> 9608.78
G16: =IF(A16="Despesas",E16*-1,IF(A16="Receitas",E16,0)) -> 0 | H16: =H15+G16 -> 9608.78
G17: =IF(A17="Despesas",E17*-1,IF(A17="Receitas",E17,0)) -> 0 | H17: =H16+G17 -> 9608.78
G18: =IF(A18="Despesas",E18*-1,IF(A18="Receitas",E18,0)) -> 0 | H18: =H17+G18 -> 9608.78
... G206: =IF(A206="Despesas",E206*-1,IF(A206="Receitas",E206,0)) -> 0 | H206: =H205+G206 -> 9608.78
A207: Fim | B207: FIM | C207: Fim | D207: Fim | E207: Fim | F207: Fim | G207: Fim | H207: FIM

Sheet AGO
C1: Agosto | F1: Preencha com o Saldo Inicial » | H1: SALDO ANTERIOR:
H2: =JUL!H206 -> 9608.78
A5: Tipo | B5: Categoria | C5: Forma de Pagamento | D5: Observações | E5: Valor | F5: Data | G5: MOV | H5: Saldo
D6: SALDO INICIAL | E6: =H2 -> 9608.78 | F6: 46234 | G6: =E6 -> 9608.78 | H6: =E6 -> 9608.78
G7: =IF(A7="Despesas",E7*-1,IF(A7="Receitas",E7,0)) -> 0 | H7: =H6+G7 -> 9608.78
G8: =IF(A8="Despesas",E8*-1,IF(A8="Receitas",E8,0)) -> 0 | H8: =H7+G8 -> 9608.78
G9: =IF(A9="Despesas",E9*-1,IF(A9="Receitas",E9,0)) -> 0 | H9: =H8+G9 -> 9608.78
G10: =IF(A10="Despesas",E10*-1,IF(A10="Receitas",E10,0)) -> 0 | H10: =H9+G10 -> 9608.78
G11: =IF(A11="Despesas",E11*-1,IF(A11="Receitas",E11,0)) -> 0 | H11: =H10+G11 -> 9608.78
G12: =IF(A12="Despesas",E12*-1,IF(A12="Receitas",E12,0)) -> 0 | H12: =H11+G12 -> 9608.78
G13: =IF(A13="Despesas",E13*-1,IF(A13="Receitas",E13,0)) -> 0 | H13: =H12+G13 -> 9608.78
G14: =IF(A14="Despesas",E14*-1,IF(A14="Receitas",E14,0)) -> 0 | H14: =H13+G14 -> 9608.78
G15: =IF(A15="Despesas",E15*-1,IF(A15="Receitas",E15,0)) -> 0 | H15: =H14+G15 -> 9608.78
G16: =IF(A16="Despesas",E16*-1,IF(A16="Receitas",E16,0)) -> 0 | H16: =H15+G16 -> 9608.78
G17: =IF(A17="Despesas",E17*-1,IF(A17="Receitas",E17,0)) -> 0 | H17: =H16+G17 -> 9608.78
G18: =IF(A18="Despesas",E18*-1,IF(A18="Receitas",E18,0)) -> 0 | H18: =H17+G18 -> 9608.78
... G206: =IF(A206="Despesas",E206*-1,IF(A206="Receitas",E206,0)) -> 0 | H206: =H205+G206 -> 9608.78
A207: Fim | B207: FIM | C207: Fim | D207: Fim | E207: Fim | F207: Fim | G207: Fim | H207: FIM

Sheet SET
C1: Setembro | F1: Preencha com o Saldo Inicial » | H1: SALDO ANTERIOR:
H2: =AGO!H206 -> 9608.78
A5: Tipo | B5: Categoria | C5: Forma de Pagamento | D5: Observações | E5: Valor | F5: Data | G5: MOV | H5: Saldo
D6: SALDO INICIAL | E6: =H2 -> 9608.78 | F6: 46265 | G6: =E6 -> 9608.78 | H6: =E6 -> 9608.78
G7: =IF(A7="Despesas",E7*-1,IF(A7="Receitas",E7,0)) -> 0 | H7: =H6+G7 -> 9608.78
G8: =IF(A8="Despesas",E8*-1,IF(A8="Receitas",E8,0)) -> 0 | H8: =H7+G8 -> 9608.78
G9: =IF(A9="Despesas",E9*-1,IF(A9="Receitas",E9,0)) -> 0 | H9: =H8+G9 -> 9608.78
G10: =IF(A10="Despesas",E10*-1,IF(A10="Receitas",E10,0)) -> 0 | H10: =H9+G10 -> 9608.78
G11: =IF(A11="Despesas",E11*-1,IF(A11="Receitas",E11,0)) -> 0 | H11: =H10+G11 -> 9608.78
G12: =IF(A12="Despesas",E12*-1,IF(A12="Receitas",E12,0)) -> 0 | H12: =H11+G12 -> 9608.78
G13: =IF(A13="Despesas",E13*-1,IF(A13="Receitas",E13,0)) -> 0 | H13: =H12+G13 -> 9608.78
G14: =IF(A14="Despesas",E14*-1,IF(A14="Receitas",E14,0)) -> 0 | H14: =H13+G14 -> 9608.78
G15: =IF(A15="Despesas",E15*-1,IF(A15="Receitas",E15,0)) -> 0 | H15: =H14+G15 -> 9608.78
G16: =IF(A16="Despesas",E16*-1,IF(A16="Receitas",E16,0)) -> 0 | H16: =H15+G16 -> 9608.78
G17: =IF(A17="Despesas",E17*-1,IF(A17="Receitas",E17,0)) -> 0 | H17: =H16+G17 -> 9608.78
G18: =IF(A18="Despesas",E18*-1,IF(A18="Receitas",E18,0)) -> 0 | H18: =H17+G18 -> 9608.78
... G206: =IF(A206="Despesas",E206*-1,IF(A206="Receitas",E206,0)) -> 0 | H206: =H205+G206 -> 9608.78
A207: Fim | B207: FIM | C207: Fim | D207: Fim | E207: Fim | F207: Fim | G207: Fim | H207: FIM

Sheet OUT
C1: Outubro | F1: Preencha com o Saldo Inicial » | H1: SALDO ANTERIOR:
H2: =SET!H206 -> 9608.78
A5: Tipo | B5: Categoria | C5: Forma de Pagamento | D5: Observações | E5: Valor | F5: Data | G5: MOV | H5: Saldo
D6: SALDO INICIAL | E6: =H2 -> 9608.78 | F6: 46295 | G6: =E6 -> 9608.78 | H6: =E6 -> 9608.78
G7: =IF(A7="Despesas",E7*-1,IF(A7="Receitas",E7,0)) -> 0 | H7: =H6+G7 -> 9608.78
G8: =IF(A8="Despesas",E8*-1,IF(A8="Receitas",E8,0)) -> 0 | H8: =H7+G8 -> 9608.78
G9: =IF(A9="Despesas",E9*-1,IF(A9="Receitas",E9,0)) -> 0 | H9: =H8+G9 -> 9608.78
G10: =IF(A10="Despesas",E10*-1,IF(A10="Receitas",E10,0)) -> 0 | H10: =H9+G10 -> 9608.78
G11: =IF(A11="Despesas",E11*-1,IF(A11="Receitas",E11,0)) -> 0 | H11: =H10+G11 -> 9608.78
G12: =IF(A12="Despesas",E12*-1,IF(A12="Receitas",E12,0)) -> 0 | H12: =H11+G12 -> 9608.78
G13: =IF(A13="Despesas",E13*-1,IF(A13="Receitas",E13,0)) -> 0 | H13: =H12+G13 -> 9608.78
G14: =IF(A14="Despesas",E14*-1,IF(A14="Receitas",E14,0)) -> 0 | H14: =H13+G14 -> 9608.78
G15: =IF(A15="Despesas",E15*-1,IF(A15="Receitas",E15,0)) -> 0 | H15: =H14+G15 -> 9608.78
G16: =IF(A16="Despesas",E16*-1,IF(A16="Receitas",E16,0)) -> 0 | H16: =H15+G16 -> 9608.78
G17: =IF(A17="Despesas",E17*-1,IF(A17="Receitas",E17,0)) -> 0 | H17: =H16+G17 -> 9608.78
G18: =IF(A18="Despesas",E18*-1,IF(A18="Receitas",E18,0)) -> 0 | H18: =H17+G18 -> 9608.78
... G206: =IF(A206="Despesas",E206*-1,IF(A206="Receitas",E206,0)) -> 0 | H206: =H205+G206 -> 9608.78
A207: Fim | B207: FIM | C207: Fim | D207: Fim | E207: Fim | F207: Fim | G207: Fim | H207: FIM

Sheet NOV
C1: Novembro | F1: Preencha com o Saldo Inicial » | H1: SALDO ANTERIOR:
H2: =OUT!H206 -> 9608.78
A5: Tipo | B5: Categoria | C5: Forma de Pagamento | D5: Observações | E5: Valor | F5: Data | G5: MOV | H5: Saldo
D6: SALDO INICIAL | E6: =H2 -> 9608.78 | F6: 46326 | G6: =E6 -> 9608.78 | H6: =E6 -> 9608.78
G7: =IF(A7="Despesas",E7*-1,IF(A7="Receitas",E7,0)) -> 0 | H7: =H6+G7 -> 9608.78
G8: =IF(A8="Despesas",E8*-1,IF(A8="Receitas",E8,0)) -> 0 | H8: =H7+G8 -> 9608.78
G9: =IF(A9="Despesas",E9*-1,IF(A9="Receitas",E9,0)) -> 0 | H9: =H8+G9 -> 9608.78
G10: =IF(A10="Despesas",E10*-1,IF(A10="Receitas",E10,0)) -> 0 | H10: =H9+G10 -> 9608.78
G11: =IF(A11="Despesas",E11*-1,IF(A11="Receitas",E11,0)) -> 0 | H11: =H10+G11 -> 9608.78
G12: =IF(A12="Despesas",E12*-1,IF(A12="Receitas",E12,0)) -> 0 | H12: =H11+G12 -> 9608.78
G13: =IF(A13="Despesas",E13*-1,IF(A13="Receitas",E13,0)) -> 0 | H13: =H12+G13 -> 9608.78
G14: =IF(A14="Despesas",E14*-1,IF(A14="Receitas",E14,0)) -> 0 | H14: =H13+G14 -> 9608.78
G15: =IF(A15="Despesas",E15*-1,IF(A15="Receitas",E15,0)) -> 0 | H15: =H14+G15 -> 9608.78
G16: =IF(A16="Despesas",E16*-1,IF(A16="Receitas",E16,0)) -> 0 | H16: =H15+G16 -> 9608.78
G17: =IF(A17="Despesas",E17*-1,IF(A17="Receitas",E17,0)) -> 0 | H17: =H16+G17 -> 9608.78
G18: =IF(A18="Despesas",E18*-1,IF(A18="Receitas",E18,0)) -> 0 | H18: =H17+G18 -> 9608.78
... G206: =IF(A206="Despesas",E206*-1,IF(A206="Receitas",E206,0)) -> 0 | H206: =H205+G206 -> 9608.78
A207: Fim | B207: FIM | C207: Fim | D207: Fim | E207: Fim | F207: Fim | G207: Fim | H207: FIM

Sheet DEZ
C1: Dezembro | F1: Preencha com o Saldo Inicial » | H1: SALDO ANTERIOR:
H2: =NOV!H206 -> 9608.78
A5: Tipo | B5: Categoria | C5: Forma de Pagamento | D5: Observações | E5: Valor | F5: Data | G5: MOV | H5: Saldo
D6: SALDO INICIAL | E6: =H2 -> 9608.78 | F6: 46356 | G6: =E6 -> 9608.78 | H6: =E6 -> 9608.78
G7: =IF(A7="Despesas",E7*-1,IF(A7="Receitas",E7,0)) -> 0 | H7: =H6+G7 -> 9608.78
G8: =IF(A8="Despesas",E8*-1,IF(A8="Receitas",E8,0)) -> 0 | H8: =H7+G8 -> 9608.78
G9: =IF(A9="Despesas",E9*-1,IF(A9="Receitas",E9,0)) -> 0 | H9: =H8+G9 -> 9608.78
G10: =IF(A10="Despesas",E10*-1,IF(A10="Receitas",E10,0)) -> 0 | H10: =H9+G10 -> 9608.78
G11: =IF(A11="Despesas",E11*-1,IF(A11="Receitas",E11,0)) -> 0 | H11: =H10+G11 -> 9608.78
G12: =IF(A12="Despesas",E12*-1,IF(A12="Receitas",E12,0)) -> 0 | H12: =H11+G12 -> 9608.78
G13: =IF(A13="Despesas",E13*-1,IF(A13="Receitas",E13,0)) -> 0 | H13: =H12+G13 -> 9608.78
G14: =IF(A14="Despesas",E14*-1,IF(A14="Receitas",E14,0)) -> 0 | H14: =H13+G14 -> 9608.78
G15: =IF(A15="Despesas",E15*-1,IF(A15="Receitas",E15,0)) -> 0 | H15: =H14+G15 -> 9608.78
G16: =IF(A16="Despesas",E16*-1,IF(A16="Receitas",E16,0)) -> 0 | H16: =H15+G16 -> 9608.78
G17: =IF(A17="Despesas",E17*-1,IF(A17="Receitas",E17,0)) -> 0 | H17: =H16+G17 -> 9608.78
G18: =IF(A18="Despesas",E18*-1,IF(A18="Receitas",E18,0)) -> 0 | H18: =H17+G18 -> 9608.78
... G206: =IF(A206="Despesas",E206*-1,IF(A206="Receitas",E206,0)) -> 0 | H206: =H205+G206 -> 9608.78
A207: Fim | B207: FIM | C207: Fim | D207: Fim | E207: Fim | F207: Fim | G207: Fim | H207: FIM
